django_base_templates/__init__.py
django_base_templates-0.1.dist-info/METADATA
django_base_templates-0.1.dist-info/WHEEL
django_base_templates-0.1.dist-info/top_level.txt
django_base_templates-0.1.dist-info/RECORD
