Metadata-Version: 2.1
Name: django-base-templates
Version: 0.1
Summary: Adding base templates for django apps
Home-page: UNKNOWN
Author: RAKOTONIAINA Harry Yves
Author-email: iharrysh.rakotoniaina@gmail.com
License: @H._T Free
Platform: UNKNOWN
Classifier: Development Status :: 3 - Alpha
Classifier: Intended Audience :: Developers
Classifier: Programming Language :: Python :: 3.10
Classifier: Programming Language :: Python :: 3.11
Classifier: Topic :: Utilities
